aws_accounts/_jsii/__init__.py
aws_accounts/_jsii/aws-accounts@0.0.3.jsii.tgz
aws_accounts-0.0.3.dist-info/LICENSE
aws_accounts-0.0.3.dist-info/METADATA
aws_accounts-0.0.3.dist-info/WHEEL
aws_accounts-0.0.3.dist-info/top_level.txt
aws_accounts-0.0.3.dist-info/RECORD
