Metadata-Version: 2.1
Name: aws-accounts
Version: 0.0.3
Summary: aws-accounts
Home-page: https://github.com/mmuller88/aws-accounts
Author: martinmueller.dev<damadden88@googlemail.com>
License: Apache-2.0
Project-URL: Source, https://github.com/mmuller88/aws-accounts
Platform: UNKNOWN
Classifier: Intended Audience :: Developers
Classifier: Operating System :: OS Independent
Classifier: Programming Language :: JavaScript
Classifier: Programming Language :: Python :: 3 :: Only
Classifier: Programming Language :: Python :: 3.7
Classifier: Programming Language :: Python :: 3.8
Classifier: Programming Language :: Python :: 3.9
Classifier: Programming Language :: Python :: 3.10
Classifier: Typing :: Typed
Classifier: Development Status :: 5 - Production/Stable
Classifier: License :: OSI Approved
Requires-Python: ~=3.7
License-File: LICENSE
Requires-Dist: jsii (<2.0.0,>=1.58.0)
Requires-Dist: publication (>=0.0.3)
